{
  "documents": [
    {
      "name": "ceptra_specification",
      "path": "../docs/specification.md",
      "sha256": "6d982e765df2fbc0fdb9bc271fb6149f885890bb5b6b5c5b423b1d8c0e0ebe7c",
      "clause_tag_coverage": 1.0,
      "document_type": "spec"
    },
    {
      "name": "clustor_specification",
      "path": "../../clustor/docs/specification.md",
      "sha256": "9ca2d2a6a135ad02b8f1d3cb6a609d3adf61dccc8a3516c3b631936cf80e9bad",
      "clause_tag_coverage": 1.0,
      "document_type": "spec"
    },
    {
      "name": "ceptra_telemetry_catalog",
      "path": "../telemetry/catalog.json",
      "sha256": "cc69bab877d9285e856600e52ae9e59f5bf243e7677d415d217d71bfdc3884a8",
      "document_type": "telemetry"
    }
  ],
  "children": []
}
